{
  "minecraft:recipes/building_blocks/polished_andesite_slab_from_polished_andesite_stonecutting": {
    "criteria": {
      "has_polished_andesite": "2022-02-09 10:34:28 +0100"
    },
    "done": true
  },
  "minecraft:recipes/building_blocks/polished_andesite_slab": {
    "criteria": {
      "has_polished_andesite": "2022-02-09 10:34:28 +0100"
    },
    "done": true
  },
  "minecraft:recipes/decorations/magenta_glazed_terracotta": {
    "criteria": {
      "has_magenta_terracotta": "2022-02-09 10:48:18 +0100"
    },
    "done": true
  },
  "minecraft:recipes/decorations/spruce_sign": {
    "criteria": {
      "has_spruce_planks": "2022-02-09 10:43:47 +0100"
    },
    "done": true
  },
  "minecraft:recipes/decorations/spruce_fence": {
    "criteria": {
      "has_planks": "2022-02-09 10:43:47 +0100"
    },
    "done": true
  },
  "minecraft:recipes/decorations/light_blue_glazed_terracotta": {
    "criteria": {
      "has_light_blue_terracotta": "2022-02-09 10:51:41 +0100"
    },
    "done": true
  },
  "minecraft:recipes/building_blocks/spruce_slab": {
    "criteria": {
      "has_planks": "2022-02-09 10:43:47 +0100"
    },
    "done": true
  },
  "minecraft:recipes/redstone/spruce_door": {
    "criteria": {
      "has_planks": "2022-02-09 10:43:47 +0100"
    },
    "done": true
  },
  "minecraft:recipes/building_blocks/polished_andesite_stairs": {
    "criteria": {
      "has_polished_andesite": "2022-02-09 10:34:28 +0100"
    },
    "done": true
  },
  "minecraft:recipes/building_blocks/polished_andesite_stairs_from_polished_andesite_stonecutting": {
    "criteria": {
      "has_polished_andesite": "2022-02-09 10:34:28 +0100"
    },
    "done": true
  },
  "minecraft:recipes/redstone/spruce_fence_gate": {
    "criteria": {
      "has_planks": "2022-02-09 10:43:47 +0100"
    },
    "done": true
  },
  "minecraft:recipes/building_blocks/spruce_stairs": {
    "criteria": {
      "has_planks": "2022-02-09 10:43:47 +0100"
    },
    "done": true
  },
  "minecraft:adventure/adventuring_time": {
    "criteria": {
      "minecraft:plains": "2022-02-09 10:33:57 +0100"
    },
    "done": false
  },
  "minecraft:recipes/redstone/spruce_trapdoor": {
    "criteria": {
      "has_planks": "2022-02-09 10:43:47 +0100"
    },
    "done": true
  },
  "minecraft:recipes/decorations/armor_stand": {
    "criteria": {
      "has_stone_slab": "2022-02-09 10:46:03 +0100"
    },
    "done": true
  },
  "minecraft:recipes/decorations/crafting_table": {
    "criteria": {
      "has_planks": "2022-02-09 10:43:47 +0100"
    },
    "done": true
  },
  "minecraft:recipes/redstone/redstone": {
    "criteria": {
      "has_redstone_block": "2022-02-09 10:47:03 +0100"
    },
    "done": true
  },
  "minecraft:recipes/decorations/composter": {
    "criteria": {
      "has_wood_slab": "2022-02-09 11:02:15 +0100"
    },
    "done": true
  },
  "minecraft:husbandry/root": {
    "criteria": {
      "consumed_item": "2022-02-09 11:36:21 +0100"
    },
    "done": true
  },
  "minecraft:recipes/decorations/chest": {
    "criteria": {
      "has_lots_of_items": "2022-02-09 10:47:00 +0100"
    },
    "done": true
  },
  "minecraft:end/elytra": {
    "criteria": {
      "elytra": "2022-02-09 10:40:50 +0100"
    },
    "done": true
  },
  "minecraft:recipes/redstone/spruce_button": {
    "criteria": {
      "has_planks": "2022-02-09 10:43:47 +0100"
    },
    "done": true
  },
  "minecraft:recipes/decorations/barrel": {
    "criteria": {
      "has_planks": "2022-02-09 10:43:47 +0100"
    },
    "done": true
  },
  "minecraft:recipes/decorations/blue_glazed_terracotta": {
    "criteria": {
      "has_blue_terracotta": "2022-02-09 10:48:27 +0100"
    },
    "done": true
  },
  "minecraft:recipes/redstone/spruce_pressure_plate": {
    "criteria": {
      "has_planks": "2022-02-09 10:43:47 +0100"
    },
    "done": true
  },
  "minecraft:recipes/decorations/pink_glazed_terracotta": {
    "criteria": {
      "has_pink_terracotta": "2022-02-09 10:52:40 +0100"
    },
    "done": true
  },
  "minecraft:recipes/misc/stick": {
    "criteria": {
      "has_planks": "2022-02-09 10:43:47 +0100"
    },
    "done": true
  },
  "minecraft:recipes/decorations/purple_glazed_terracotta": {
    "criteria": {
      "has_purple_terracotta": "2022-02-09 10:48:15 +0100"
    },
    "done": true
  },
  "minecraft:recipes/decorations/white_glazed_terracotta": {
    "criteria": {
      "has_white_terracotta": "2022-02-09 11:23:17 +0100"
    },
    "done": true
  },
  "DataVersion": 2586
}